py4spice/__init__.py
py4spice/analyses-orig.py
py4spice/analyses.py
py4spice/control.py
py4spice/kicad.py
py4spice/netlist.py
py4spice/oscilloscope.mplstyle
py4spice/plot.py
py4spice/print_section.py
py4spice/simulate.py
py4spice/to_pandas.py
py4spice/vectors.py
py4spice-0.0.1.dist-info/METADATA
py4spice-0.0.1.dist-info/WHEEL
py4spice-0.0.1.dist-info/top_level.txt
py4spice-0.0.1.dist-info/RECORD
