Metadata-Version: 2.1
Name: py4spice
Version: 0.0.1
Summary: Python for Spice
Author-email: Mark Chadwick <mark.chadwick@techsharpen.com>
License: MIT License
Project-URL: repository, https://github.com/astorguy/py4spice
Keywords: ngspice,spice,simulation
Classifier: Programming Language :: Python :: 3
Requires-Python: >=3.11
